gitfind/__init__.py
gitfind/cli.py
gitfind/core.py
gitfind/utils.py
gitfind-0.1.1.dist-info/licenses/LICENSE
tests/__init__.py
tests/test_core.py
gitfind-0.1.1.dist-info/METADATA
gitfind-0.1.1.dist-info/WHEEL
gitfind-0.1.1.dist-info/entry_points.txt
gitfind-0.1.1.dist-info/top_level.txt
gitfind-0.1.1.dist-info/RECORD
